allocineAPI/__init__.py
allocineAPI/allocineAPI.py
allocine_seances-0.0.13.dist-info/LICENSE
allocine_seances-0.0.13.dist-info/METADATA
allocine_seances-0.0.13.dist-info/WHEEL
allocine_seances-0.0.13.dist-info/top_level.txt
allocine_seances-0.0.13.dist-info/RECORD
