Metadata-Version: 2.2
Name: allocine-seances
Version: 0.0.13
Summary: Récupération des scéances de cinémas sur allociné
Author-email: lefevre-dev <louislefevre.dev@gmail.com>
License: MIT License
Project-URL: Homepage, https://github.com/lefevre-dev/AllocineAPI
Project-URL: Bug Tracker, https://github.com/lefevre-dev/AllocineAPI/issues
Classifier: Programming Language :: Python :: 3
Classifier: License :: OSI Approved :: MIT License
Classifier: Operating System :: OS Independent
Requires-Python: >=3.7
License-File: LICENSE
Requires-Dist: beautifulsoup4
